Metadata-Version: 2.1
Name: ceotr-file
Version: 1.0.1
Summary: Common python library for CEOTR data team
Home-page: https://gitlab.oceantrack.org/ceotr-public/ceotr_app_common/ceotr_file
Author: CEOTR
Author-email: support@ceotr.ca
License: GNU General Public License v3 (GPLv3)
License-File: LICENSE.md
